aeca/__init__.py
aeca/channel.py
aeca/document_db.py
aeca/fts_analysis_pipeline.py
aeca/key_value_db.py
aeca/sentence_transformer.py
aeca/protobuf/__init__.py
aeca/protobuf/document_db_pb2.py
aeca/protobuf/document_db_pb2_grpc.py
aeca/protobuf/document_pb2.py
aeca/protobuf/fts_analysis_pipeline_pb2.py
aeca/protobuf/fts_analysis_pipeline_pb2_grpc.py
aeca/protobuf/key_value_db_pb2.py
aeca/protobuf/key_value_db_pb2_grpc.py
aeca/protobuf/sentence_transformer_pb2.py
aeca/protobuf/sentence_transformer_pb2_grpc.py
aeca/protobuf/workspaces_pb2.py
aeca/protobuf/workspaces_pb2_grpc.py
aeca-1.0.0.dev1.dist-info/LICENSE
aeca-1.0.0.dev1.dist-info/METADATA
aeca-1.0.0.dev1.dist-info/WHEEL
aeca-1.0.0.dev1.dist-info/top_level.txt
aeca-1.0.0.dev1.dist-info/RECORD
